Metadata-Version: 2.1
Name: bba_pipeline
Version: 1.3.1
Summary: Package defining a SnakeMake pipeline to create the Blue Brain Atlas datasetsand push them into Nexus.
Home-page: https://github.com/BlueBrain/bbp-atlas-pipeline
Author: Blue Brain Project, EPFL
License: Apache-2.0
Requires-Python: >=3.9
License-File: LICENSE.txt
License-File: AUTHORS.txt
Requires-Dist: nexusforge >=0.8.2
Requires-Dist: click >=7.0
Requires-Dist: numpy >=1.19
Requires-Dist: pynrrd >=0.4.0
Requires-Dist: PyYAML >=5.3.1
Requires-Dist: voxcell
Requires-Dist: pulp ==2.7.0
Requires-Dist: snakemake ==7.32.3
Requires-Dist: blue-cwl
Requires-Dist: python-gitlab
Provides-Extra: dev
Requires-Dist: pytest >=4.3 ; extra == 'dev'
Requires-Dist: pytest-cov >=2.8.0 ; extra == 'dev'
Requires-Dist: blue-brain-token-fetch >=1.0.0 ; extra == 'dev'
Provides-Extra: docs
Requires-Dist: sphinx ==7.1.2 ; extra == 'docs'
Requires-Dist: sphinx-bluebrain-theme ; extra == 'docs'
Requires-Dist: myst-parser ; extra == 'docs'
